wexapi/__init__.py
wexapi/common.py
wexapi/keyhandler.py
wexapi/public.py
wexapi/scraping.py
wexapi/trade.py
wexapi/utils.py
wexapi/models/__init__.py
wexapi/models/account_info.py
wexapi/models/cancel_order_result.py
wexapi/models/order.py
wexapi/models/order_info.py
wexapi/models/pair_info.py
wexapi/models/ticker.py
wexapi/models/trade.py
wexapi/models/trade_history.py
wexapi/models/trade_result.py
wexapi/models/trans_history.py
wexapi/test/__init__.py
wexapi/test/test_keyhandler.py
wexapi/test/test_public.py
wexapi/test/test_scraping.py
wexapi/test/test_trade.py
wexapi/test/test_utils.py
wexapi/test/models/__init__.py
wexapi/test/models/test_account_info.py
wexapi/test/models/test_cancel_order_result.py
wexapi/test/models/test_order.py
wexapi/test/models/test_order_info.py
wexapi/test/models/test_pair_info.py
wexapi/test/models/test_ticker.py
wexapi/test/models/test_trade.py
wexapi/test/models/test_trade_history.py
wexapi/test/models/test_trade_result.py
wexapi/test/models/test_trans_history.py
wexapi-0.1.0.dist-info/METADATA
wexapi-0.1.0.dist-info/RECORD
wexapi-0.1.0.dist-info/WHEEL
wexapi-0.1.0.dist-info/top_level.txt
