Metadata-Version: 2.1
Name: wexapi
Version: 0.1.0
Summary: Wex.nz API Client
Home-page: https://github.com/madmis/wexapi
Author: Machin Dmitro
Author-email: machin.dmitry+pypi.org@gmail.com
License: UNKNOWN
Platform: UNKNOWN
Classifier: Programming Language :: Python :: 3.6
Classifier: License :: OSI Approved :: MIT License
Classifier: Operating System :: OS Independent
